Metadata-Version: 2.1
Name: JsoNomads
Version: 1.0.3
Summary: Download nomads data from NOAA and convert the grib file to JSON
Home-page: https://draken.ee
Author: Draken TT
Author-email: info@draken.ee
License: GPLv3
Platform: UNKNOWN
Classifier: Development Status :: 5 - Production/Stable
Classifier: License :: OSI Approved :: GNU General Public License v3 (GPLv3)
Classifier: Topic :: Scientific/Engineering :: Atmospheric Science
Classifier: Topic :: Software Development :: Libraries :: Python Modules
License-File: LICENSE
